{
	"config": {
		"minWallHeight": 4,
		"maxWallHeight": 8,
		"initialHeading": 0,
		"wallThickness": 3,
		"allure": true,
		"parapet": true
		},
	"color": {
		"wallColor": [179, 1],
		"allureColor": [98],
		"turretColor": [98],
		"turretWindowColor": [192],
		"turretRoofColor": [179, 1],
		"gateColor": [113],
		"gateWallColor": [98],
		"gateFloorColor": [4],
		"decorativeStairColor": 109,
		"parapetColor": [98, 3],
		"awningColor": [126, 4],
		"awningSupportColor": 192,
		"awningBaseColor": [179, 1]
		},
	"path": [
		{"cmd": "move", "argv": 15},
		{"cmd": "cannon", "argv": "left"},
		{"cmd": "move", "argv": 15},
		{"cmd": "right", "argv": 90},
		{"cmd": "turret", "argv": [14, "flat"]},
		{"cmd": "move", "argv": 9},
		{"cmd": "cannon", "argv": "left"},
		{"cmd": "move", "argv": 5},
		{"cmd": "gate", "argv": 11},
		{"cmd": "move", "argv": 5},
		{"cmd": "cannon", "argv": "left"},
		{"cmd": "move", "argv": 9},
		{"cmd": "right", "argv": 90},
		{"cmd": "turret", "argv": [16, "flat"]},
		{"cmd": "move", "argv": 15},
		{"cmd": "cannon", "argv": "left"},
		{"cmd": "move", "argv": 15},
		{"cmd": "right", "argv": 90},
		{"cmd": "turret", "argv": [18, "flat"]},
		{"cmd": "move", "argv": 19},
		{"cmd": "cannon", "argv": "left"},
		{"cmd": "move", "argv": 18},
		{"cmd": "right", "argv": 90},
		{"cmd": "turret", "argv": [16, "flat"]}
	]
}